efrem_utils.py
efrem_utils-0.3.1.dist-info/LICENSE
efrem_utils-0.3.1.dist-info/METADATA
efrem_utils-0.3.1.dist-info/WHEEL
efrem_utils-0.3.1.dist-info/RECORD
