Metadata-Version: 2.1
Name: efrem-utils
Version: 0.3.1
Summary: Efrem's utilities
Home-page: https://github.com/NikitaNightBot/efrem-utils
Author: lone_druid
Author-email: enikita332@gmail.com
Requires-Python: >=3.11,<4.0
Classifier: Programming Language :: Python :: 3
Classifier: Programming Language :: Python :: 3.11
Project-URL: Repository, https://github.com/NikitaNightBot/efrem-utils
